pylink/__init__.py
pylink/element.py
pylink/model.py
pylink/report.py
pylink/tagged_attribute.py
pylink/utils.py
pylink/tex/budget.tex
pylink/tributaries/__init__.py
pylink/tributaries/antenna.py
pylink/tributaries/budget.py
pylink/tributaries/channel.py
pylink/tributaries/geometry.py
pylink/tributaries/hyperspectral.py
pylink/tributaries/interconnect.py
pylink/tributaries/modulation.py
pylink/tributaries/receiver.py
pylink/tributaries/transmitter.py
pylink_satcom-0.9.dist-info/LICENSE.txt
pylink_satcom-0.9.dist-info/METADATA
pylink_satcom-0.9.dist-info/WHEEL
pylink_satcom-0.9.dist-info/top_level.txt
pylink_satcom-0.9.dist-info/RECORD
