Metadata-Version: 2.1
Name: pylink-satcom
Version: 0.9
Summary: Python Link Budget System
Home-page: https://github.com/harrison-caudill/pylink
Author: Harrison Caudill
Author-email: harrison@hypersphere.org
License: UNKNOWN
Platform: UNKNOWN
Classifier: Development Status :: 4 - Beta
Classifier: Intended Audience :: Developers
Classifier: Intended Audience :: Science/Research
Classifier: Intended Audience :: Telecommunications Industry
Classifier: License :: OSI Approved :: BSD License
Classifier: Natural Language :: English
Classifier: Operating System :: OS Independent
Classifier: Programming Language :: Python :: 3
Classifier: Topic :: Communications :: Ham Radio
Classifier: Topic :: Scientific/Engineering :: Atmospheric Science
Classifier: Topic :: Scientific/Engineering :: Physics
Requires-Dist: matplotlib
Requires-Dist: jinja2
Requires-Dist: scipy
Requires-Dist: numpy
